ldap_hopper/__init__.py
ldap_hopper/cursor.py
ldap_hopper-3.3.7.dist-info/LICENSE
ldap_hopper-3.3.7.dist-info/METADATA
ldap_hopper-3.3.7.dist-info/WHEEL
ldap_hopper-3.3.7.dist-info/top_level.txt
ldap_hopper-3.3.7.dist-info/RECORD
