Metadata-Version: 2.1
Name: ldap-hopper
Version: 3.3.7
Summary: 'Client library for fast+easy access and manipulation of an LDAP directory-information-tree(DIT).'
Home-page: https://github.com/baccenfutter/ldap_hopper
Author: Brian Wiborg
Author-email: baccenfutter@c-base.org
License: UNKNOWN
Project-URL: Bug Tracker, https://github.com/baccenfutter/ldap_hopper/issues
Platform: UNKNOWN
Classifier: Programming Language :: Python :: 3
Classifier: License :: OSI Approved :: MIT License
Classifier: Operating System :: OS Independent
Requires-Python: >=3.6
License-File: LICENSE
Requires-Dist: python-ldap
Provides-Extra: dev
Requires-Dist: build ; extra == 'dev'
Requires-Dist: ipython ; extra == 'dev'
Requires-Dist: prompt-toolkit ; extra == 'dev'
Requires-Dist: pylint ; extra == 'dev'
Requires-Dist: twine ; extra == 'dev'
